nvshim/__init__.py
nvshim/core/__init__.py
nvshim/core/__main__.py
nvshim/core/shim.py
nvshim/core/shim_nvm.py
nvshim/core/tests/__init__.py
nvshim/core/tests/test_main.py
nvshim/core/tests/test_shim.py
nvshim/core/tests/test_shim_nvm.py
nvshim/core/tests/__snapshots__/test_main.ambr
nvshim/utils/__init__.py
nvshim/utils/constants.py
nvshim/utils/environment.py
nvshim/utils/message.py
nvshim/utils/process.py
nvshim/utils/tests/test_process.py
nvshim/utils/tests/__snapshots__/test_process.ambr
nvshim-1.1.2.dist-info/LICENSE
nvshim-1.1.2.dist-info/METADATA
nvshim-1.1.2.dist-info/WHEEL
nvshim-1.1.2.dist-info/entry_points.txt
nvshim-1.1.2.dist-info/top_level.txt
nvshim-1.1.2.dist-info/RECORD
