Metadata-Version: 2.1
Name: nvshim
Version: 1.1.2
Summary: Automagically use the correct version of node
Home-page: http://github.com/iamogbz/nvshim
Author: Emmanuel Ogbizi-Ugbe
Author-email: iamogbz+pypi@gmail.com
License: GNU
Keywords: node nvm node-shim shim shell nvm-shim
Platform: UNKNOWN
Classifier: Development Status :: 4 - Beta
Classifier: Environment :: Console
Classifier: Intended Audience :: Developers
Classifier: Intended Audience :: End Users/Desktop
Classifier: Intended Audience :: System Administrators
Classifier: License :: OSI Approved :: GNU General Public License (GPL)
Classifier: Operating System :: MacOS :: MacOS X
Classifier: Operating System :: Microsoft :: Windows
Classifier: Operating System :: POSIX
Classifier: Programming Language :: Python
Classifier: Topic :: Software Development
Requires-Python: >=3
Requires-Dist: colored
Requires-Dist: semver
